expo/__init__.py
expo/exporter.py
expo/utils.py
expo-0.1.1.dist-info/LICENSE
expo-0.1.1.dist-info/WHEEL
expo-0.1.1.dist-info/METADATA
expo-0.1.1.dist-info/RECORD
